licenseman/__init__.py
licenseman/data/__init__.py
licenseman/data/__test_file__
licenseman/data/spdx/schema.json
licenseman/data/spdx/schema.xsd
licenseman/data/spdx/trove_classifiers.yaml
licenseman/exception/__init__.py
licenseman/exception/data.py
licenseman/spdx/__init__.py
licenseman/spdx/entry.py
licenseman/spdx/exception.py
licenseman/spdx/exception_db.py
licenseman/spdx/exception_list.py
licenseman/spdx/expression.py
licenseman/spdx/license.py
licenseman/spdx/license_db.py
licenseman/spdx/license_list.py
licenseman/spdx/license_text.py
licenseman-0.1.0.dist-info/METADATA
licenseman-0.1.0.dist-info/WHEEL
licenseman-0.1.0.dist-info/top_level.txt
licenseman-0.1.0.dist-info/RECORD
